mcp_nefino/__init__.py
mcp_nefino/client.py
mcp_nefino/config.py
mcp_nefino/enums.py
mcp_nefino/server.py
mcp_nefino/task_manager.py
mcp_nefino/validation.py
mcp_nefino-0.1.5.dist-info/METADATA
mcp_nefino-0.1.5.dist-info/WHEEL
mcp_nefino-0.1.5.dist-info/entry_points.txt
mcp_nefino-0.1.5.dist-info/licenses/LICENSE
mcp_nefino-0.1.5.dist-info/RECORD
