Metadata-Version: 2.4
Name: mcp-nefino
Version: 0.1.5
Summary: MCP server for accessing Nefino renewable energy news API
Author-email: David Kort <david.kort@nefino.de>
License-Expression: Apache-2.0
License-File: LICENSE
Requires-Python: >=3.10
Requires-Dist: aiohttp
Requires-Dist: fastapi
Requires-Dist: mcp>=1.3.0
Requires-Dist: pydantic
Requires-Dist: python-jose
Requires-Dist: requests
